odoo/addons/storage_media_product/README.rst
odoo/addons/storage_media_product/__init__.py
odoo/addons/storage_media_product/__manifest__.py
odoo/addons/storage_media_product/i18n/storage_media_product.pot
odoo/addons/storage_media_product/models/__init__.py
odoo/addons/storage_media_product/models/product.py
odoo/addons/storage_media_product/models/product_category.py
odoo/addons/storage_media_product/security/ir.model.access.csv
odoo/addons/storage_media_product/static/description/icon.png
odoo/addons/storage_media_product/views/product.xml
odoo/addons/storage_media_product/views/product_category.xml
odoo14_addon_storage_media_product-14.0.2.3.0.dist-info/METADATA
odoo14_addon_storage_media_product-14.0.2.3.0.dist-info/WHEEL
odoo14_addon_storage_media_product-14.0.2.3.0.dist-info/top_level.txt
odoo14_addon_storage_media_product-14.0.2.3.0.dist-info/RECORD
