Metadata-Version: 2.1
Name: odoo14-addon-storage-media-product
Version: 14.0.2.3.0
Summary: Link media to products and categories
Home-page: https://github.com/OCA/storage
Author: Akretion, Odoo Community Association (OCA)
Author-email: support@odoo-community.org
License: LGPL-3
Platform: UNKNOWN
Classifier: Programming Language :: Python
Classifier: Framework :: Odoo
Classifier: Framework :: Odoo :: 14.0
Classifier: License :: OSI Approved :: GNU Lesser General Public License v3 (LGPLv3)
Requires-Python: >=3.6
Requires-Dist: odoo14-addon-storage-media
Requires-Dist: odoo <14.1dev,>=14.0a
